threadmanager/__init__.py
threadmanager/_utils.py
threadmanager/thread.py
threadmanager/thread_events.py
threadmanager/thread_group.py
threadmanager/threadutils.py
threadgroup_manager-0.1.2.dist-info/METADATA
threadgroup_manager-0.1.2.dist-info/WHEEL
threadgroup_manager-0.1.2.dist-info/top_level.txt
threadgroup_manager-0.1.2.dist-info/RECORD
