Metadata-Version: 2.4
Name: threadgroup-manager
Version: 0.1.2
Summary: A Python library for hierarchical thread group management with event-based coordination.
Author-email: Ethan D'sa <dsaethan01@gmail.com>
License: MIT
Project-URL: Repository, https://github.com/ethandsa/Thread-Management-Library
Requires-Python: >=3.7
